riscos_conv-0.0.1.dist-info/licenses/LICENSE
riscosconv/__init__.py
riscosconv/adfslib.py
riscosconv/cli.py
riscosconv/filetypes.py
riscosconv/nspark.py
riscosconv/riscos_zip.py
riscosconv/riscosiso.py
riscosconv/ro_file_meta.py
riscosconv/sprites.py
riscos_conv-0.0.1.dist-info/METADATA
riscos_conv-0.0.1.dist-info/WHEEL
riscos_conv-0.0.1.dist-info/entry_points.txt
riscos_conv-0.0.1.dist-info/top_level.txt
riscos_conv-0.0.1.dist-info/RECORD
