Metadata-Version: 2.4
Name: riscos-conv
Version: 0.0.1
Summary: Library and CLI tools to convert to/from RISC OS formats
Author: Paul Stone
Project-URL: Homepage, https://github.com/pdjstone/riscos-conv
Project-URL: Issues, https://github.com/pdjstone/riscos-conv/issues
Classifier: Programming Language :: Python :: 3
Classifier: Operating System :: OS Independent
Classifier: License :: OSI Approved :: GNU General Public License v3 (GPLv3)
Classifier: Environment :: Console
Requires-Python: >=3.10
License-File: LICENSE
Requires-Dist: toml
Requires-Dist: tomlkit
Requires-Dist: jinja2
Requires-Dist: requests
Requires-Dist: pillow
Requires-Dist: pycdlib
Dynamic: license-file
